src/__init__.py
src/requests_refresh_header.py
requests_refresh_header-0.0.1.dist-info/METADATA
requests_refresh_header-0.0.1.dist-info/WHEEL
requests_refresh_header-0.0.1.dist-info/licenses/LICENSE
requests_refresh_header-0.0.1.dist-info/RECORD
