Metadata-Version: 2.1
Name: requests_refresh_header
Version: 0.0.1
Summary: Adds support for the Refresh header in requests. Check out the README for more info.
Project-URL: Homepage, https://github.com/matthew-hajec/request_refresh_header
Project-URL: Issues, https://github.com/matthew-hajec/request_refresh_header/issues
Author-email: mhajec21 <matthew.hajec02@gmail.com>
License-File: LICENSE
Requires-Python: >=3.8
